abstract_ide/__init__.py
abstract_ide/consoles/__init__.py
abstract_ide/consoles/main.py
abstract_ide/consoles/src/__init__.py
abstract_ide/consoles/src/main.py
abstract_ide/consoles/src/apiConsole/__init__.py
abstract_ide/consoles/src/apiConsole/main.py
abstract_ide/consoles/src/apiConsole/src/__init__.py
abstract_ide/consoles/src/apiConsole/src/main.py
abstract_ide/consoles/src/apiConsole/src/imports/__init__.py
abstract_ide/consoles/src/apiConsole/src/imports/utils.py
abstract_ide/consoles/src/apiConsole/src/imports/src/__init__.py
abstract_ide/consoles/src/apiConsole/src/imports/src/constants.py
abstract_ide/consoles/src/apiConsole/src/imports/src/init_imports.py
abstract_ide/consoles/src/appRunner/__init__.py
abstract_ide/consoles/src/appRunner/main.py
abstract_ide/consoles/src/appRunner/src/__init__.py
abstract_ide/consoles/src/appRunner/src/main.py
abstract_ide/consoles/src/appRunner/src/imports/__init__.py
abstract_ide/consoles/src/appRunner/src/imports/appRunnerWorker.py
abstract_ide/consoles/src/appRunner/src/imports/logPane.py
abstract_ide/consoles/src/appRunner/src/imports/utils.py
abstract_ide/consoles/src/appRunner/src/imports/src/__init__.py
abstract_ide/consoles/src/appRunner/src/imports/src/constants.py
abstract_ide/consoles/src/appRunner/src/imports/src/init_imports.py
abstract_ide/consoles/src/appRunner/src/imports/src/launcher.py
abstract_ide/consoles/src/appRunner/src/imports/src/module_imports.py
abstract_ide/consoles/src/clipit/__init__.py
abstract_ide/consoles/src/clipit/main.py
abstract_ide/consoles/src/clipit/src/__init__.py
abstract_ide/consoles/src/databaseViewer/__init__.py
abstract_ide/consoles/src/databaseViewer/app.py
abstract_ide/consoles/src/databaseViewer/test.py
abstract_ide/consoles/src/databaseViewer/src/__init__.py
abstract_ide/consoles/src/databaseViewer/src/db_viewer(1).py
abstract_ide/consoles/src/databaseViewer/src/main.py
abstract_ide/consoles/src/databaseViewer/src/teststream.py
abstract_ide-0.0.0.371.dist-info/METADATA
abstract_ide-0.0.0.371.dist-info/WHEEL
abstract_ide-0.0.0.371.dist-info/top_level.txt
abstract_ide-0.0.0.371.dist-info/RECORD
