Metadata-Version: 2.4
Name: abstract_ide
Version: 0.0.0.371
Summary: abstract_ide
Home-page: https://github.com/AbstractEndeavors/abstract_ide
Author: putkoff
Author-email: partners@abstractendeavors.com
Classifier: Development Status :: 3 - Alpha
Classifier: Intended Audience :: Developers
Classifier: License :: OSI Approved :: MIT License
Classifier: Programming Language :: Python :: 3
Classifier: Programming Language :: Python :: 3.11
Requires-Python: >=3.6
Requires-Dist: abstract_apis
Requires-Dist: PyQt5
Requires-Dist: abstract_webtools
Requires-Dist: abstract_utilities
Requires-Dist: abstract_gui
Requires-Dist: pydot
Requires-Dist: abstract_clipit
Requires-Dist: flask
Requires-Dist: abstract_paths
Requires-Dist: PyQt6
Dynamic: author
Dynamic: author-email
Dynamic: classifier
Dynamic: description
Dynamic: description-content-type
Dynamic: home-page
Dynamic: requires-dist
Dynamic: requires-python
Dynamic: summary
